{
  "smaplan": {
    "searchConsole": {
      "period": "2026-04-25 ~ 2026-05-23",
      "topQueries": [
        {
          "query": "5g ホームルーター おすすめ 2026",
          "clicks": 0,
          "impressions": 1,
          "ctr": "0.0%",
          "position": "15.0"
        },
        {
          "query": "aiを使って通信料金の最適プランを自動で提案してもらえるの？",
          "clicks": 0,
          "impressions": 7,
          "ctr": "0.0%",
          "position": "4.1"
        },
        {
          "query": "スマホ コスト削減",
          "clicks": 0,
          "impressions": 1,
          "ctr": "0.0%",
          "position": "39.0"
        },
        {
          "query": "スマホプラン 安く 通信品質 落とさない 方法",
          "clicks": 0,
          "impressions": 10,
          "ctr": "0.0%",
          "position": "18.3"
        },
        {
          "query": "スマホプラン診断",
          "clicks": 0,
          "impressions": 2,
          "ctr": "0.0%",
          "position": "11.0"
        },
        {
          "query": "スマホ代を安くするにはどうすればいい？",
          "clicks": 0,
          "impressions": 6,
          "ctr": "0.0%",
          "position": "40.5"
        },
        {
          "query": "ドコモホームルーター ランキング",
          "clicks": 0,
          "impressions": 9,
          "ctr": "0.0%",
          "position": "68.3"
        },
        {
          "query": "ホーム ルーター 光 回線 比較",
          "clicks": 0,
          "impressions": 1,
          "ctr": "0.0%",
          "position": "29.0"
        },
        {
          "query": "ホームルーター 速度",
          "clicks": 0,
          "impressions": 2,
          "ctr": "0.0%",
          "position": "40.5"
        },
        {
          "query": "日本 スマホ代 節約 方法 2026",
          "clicks": 0,
          "impressions": 3,
          "ctr": "0.0%",
          "position": "18.7"
        }
      ],
      "topPages": [
        {
          "page": "https://smaplan.com/",
          "clicks": 3,
          "impressions": 83,
          "ctr": "3.6%",
          "position": "3.6"
        },
        {
          "page": "https://smaplan.com/blog/hikari-vs-home-router",
          "clicks": 0,
          "impressions": 31,
          "ctr": "0.0%",
          "position": "14.6"
        },
        {
          "page": "https://smaplan.com/blog/home-router-ranking",
          "clicks": 0,
          "impressions": 19,
          "ctr": "0.0%",
          "position": "37.1"
        },
        {
          "page": "https://smaplan.com/blog/internet-line-beginners",
          "clicks": 0,
          "impressions": 3,
          "ctr": "0.0%",
          "position": "14.0"
        },
        {
          "page": "https://smaplan.com/blog/save-money",
          "clicks": 0,
          "impressions": 39,
          "ctr": "0.0%",
          "position": "18.6"
        },
        {
          "page": "https://smaplan.com/carrier/ymobile_simple3_m",
          "clicks": 0,
          "impressions": 13,
          "ctr": "0.0%",
          "position": "9.5"
        }
      ]
    },
    "ga4": [],
    "repo": "C:/Users/suhr5/erabook"
  },
  "gacha-now": {
    "searchConsole": {
      "period": "2026-04-25 ~ 2026-05-23",
      "topQueries": [
        {
          "query": "ガチャ 新作",
          "clicks": 0,
          "impressions": 1,
          "ctr": "0.0%",
          "position": "8.0"
        },
        {
          "query": "ガチャガチャ 新作情報",
          "clicks": 0,
          "impressions": 2,
          "ctr": "0.0%",
          "position": "11.0"
        },
        {
          "query": "ガチャガチャ 最新情報",
          "clicks": 0,
          "impressions": 5,
          "ctr": "0.0%",
          "position": "10.4"
        },
        {
          "query": "ガチャ新作",
          "clicks": 0,
          "impressions": 1,
          "ctr": "0.0%",
          "position": "8.0"
        },
        {
          "query": "ガチャ新作情報",
          "clicks": 0,
          "impressions": 2,
          "ctr": "0.0%",
          "position": "9.5"
        },
        {
          "query": "グローグーいっぱいコレクション2",
          "clicks": 0,
          "impressions": 1,
          "ctr": "0.0%",
          "position": "34.0"
        },
        {
          "query": "スポンジボブ ガチャガチャ 新作",
          "clicks": 0,
          "impressions": 3,
          "ctr": "0.0%",
          "position": "11.0"
        },
        {
          "query": "スポンジボブ ガチャガチャ 最新",
          "clicks": 0,
          "impressions": 1,
          "ctr": "0.0%",
          "position": "15.0"
        },
        {
          "query": "今日ガチャガチャ",
          "clicks": 0,
          "impressions": 1,
          "ctr": "0.0%",
          "position": "12.0"
        }
      ],
      "topPages": [
        {
          "page": "https://gacha-now.net/",
          "clicks": 11,
          "impressions": 47,
          "ctr": "23.4%",
          "position": "6.9"
        },
        {
          "page": "https://gacha-now.net/brand/heroaca",
          "clicks": 0,
          "impressions": 4,
          "ctr": "0.0%",
          "position": "7.0"
        },
        {
          "page": "https://gacha-now.net/brand/madoka",
          "clicks": 0,
          "impressions": 1,
          "ctr": "0.0%",
          "position": "4.0"
        },
        {
          "page": "https://gacha-now.net/brand/spongebob",
          "clicks": 0,
          "impressions": 9,
          "ctr": "0.0%",
          "position": "11.6"
        },
        {
          "page": "https://gacha-now.net/item/gacha-0fc3ee2b",
          "clicks": 0,
          "impressions": 1,
          "ctr": "0.0%",
          "position": "40.0"
        },
        {
          "page": "https://gacha-now.net/item/gacha-2ce24906",
          "clicks": 0,
          "impressions": 1,
          "ctr": "0.0%",
          "position": "47.0"
        },
        {
          "page": "https://gacha-now.net/item/gacha-34eb5e6a",
          "clicks": 0,
          "impressions": 2,
          "ctr": "0.0%",
          "position": "16.0"
        },
        {
          "page": "https://gacha-now.net/item/gacha-38beaa7c",
          "clicks": 0,
          "impressions": 1,
          "ctr": "0.0%",
          "position": "8.0"
        },
        {
          "page": "https://gacha-now.net/item/gacha-4529de6a",
          "clicks": 0,
          "impressions": 1,
          "ctr": "0.0%",
          "position": "34.0"
        },
        {
          "page": "https://gacha-now.net/item/one-piece-3-0d891481",
          "clicks": 0,
          "impressions": 3,
          "ctr": "0.0%",
          "position": "16.0"
        }
      ]
    },
    "ga4": [],
    "repo": "C:/Users/suhr5/gacha-now"
  },
  "orenocosme": {
    "searchConsole": {
      "period": "2026-04-25 ~ 2026-05-23",
      "topQueries": [
        {
          "query": "メンズ クリーム 口コミ",
          "clicks": 0,
          "impressions": 2,
          "ctr": "0.0%",
          "position": "36.0"
        },
        {
          "query": "メンズコスメ 口コミ",
          "clicks": 0,
          "impressions": 49,
          "ctr": "0.0%",
          "position": "25.9"
        }
      ],
      "topPages": [
        {
          "page": "https://oreno-cosme.com/",
          "clicks": 2,
          "impressions": 58,
          "ctr": "3.4%",
          "position": "24.6"
        },
        {
          "page": "https://oreno-cosme.com/products?brand=null-cosme",
          "clicks": 0,
          "impressions": 1,
          "ctr": "0.0%",
          "position": "1.0"
        }
      ]
    },
    "ga4": [],
    "repo": "C:/Users/suhr5/orenocosme"
  }
}